easy_plot/__init__.py
easy_plot/_pca.py
easy_plot/cleaning.py
easy_plot/contour.py
easy_plot/density.py
easy_plot/distribution.py
easy_plot/heatmap.py
easy_plot/histogram.py
easy_plot/line.py
easy_plot/scatter.py
easy_plot/scatter_matrix.py
easy_plot/surface.py
easy_plot/trend.py
easy_plot-0.1.0.dist-info/LICENSE.txt
easy_plot-0.1.0.dist-info/METADATA
easy_plot-0.1.0.dist-info/WHEEL
easy_plot-0.1.0.dist-info/top_level.txt
easy_plot-0.1.0.dist-info/RECORD
