Metadata-Version: 2.1
Name: easy-plot
Version: 0.1.0
Summary: Easy Statistical Visualization
Home-page: https://github.com/zachbateman/easy_plot.git
Author: Zach Bateman
License: MIT
Download-URL: https://github.com/zachbateman/easy_plot/archive/v_0.1.0.tar.gz
Keywords: STATISTICS,VISUALIZATION,SIMPLE,EASY,PLOT
Platform: UNKNOWN
Classifier: Development Status :: 3 - Alpha
Classifier: License :: OSI Approved :: MIT License
Classifier: Programming Language :: Python :: 3
Classifier: Programming Language :: Python :: 3.7
Classifier: Programming Language :: Python :: 3.8
Classifier: Programming Language :: Python :: 3.9
Requires-Dist: matplotlib
Requires-Dist: seaborn
Requires-Dist: pandas
